engNotation/engNotation.py
eng_notation-1.0.0.dist-info/LICENSE
eng_notation-1.0.0.dist-info/METADATA
eng_notation-1.0.0.dist-info/WHEEL
eng_notation-1.0.0.dist-info/top_level.txt
eng_notation-1.0.0.dist-info/RECORD
