Metadata-Version: 2.2
Name: eng_Notation
Version: 1.0.0
Summary: Converts Numbers Into Engineering Notation
Author-email: Bretton Scarbrough <bretton.scarbrough@gmail.com>
License-File: LICENSE
Requires-Dist: numpy
